sksacred/__init__.py
scikit_sacred-0.1.9.dist-info/LICENSE
scikit_sacred-0.1.9.dist-info/METADATA
scikit_sacred-0.1.9.dist-info/WHEEL
scikit_sacred-0.1.9.dist-info/top_level.txt
scikit_sacred-0.1.9.dist-info/RECORD
