Metadata-Version: 2.1
Name: scikit-sacred
Version: 0.1.9
Summary: Scikit-learn-compatible Sacred experiments
Home-page: https://github.com/daviddiazvico/scikit-sacred
Author: David Diaz Vico
Author-email: david.diaz.vico@outlook.com
License: UNKNOWN
Download-URL: https://github.com/daviddiazvico/scikit-sacred/archive/v0.1.9.tar.gz
Keywords: sacred
Platform: UNKNOWN
Classifier: Intended Audience :: Science/Research
Classifier: Topic :: Scientific/Engineering
Classifier: Programming Language :: Python
Classifier: Programming Language :: Python :: 3
Classifier: Programming Language :: Python :: 3.6
Classifier: Programming Language :: Python :: 3.7
Requires-Dist: sacred
